unity_mcp_client/__init__.py
unity_mcp_client/client.py
mcp_client-0.1.0.dist-info/LICENSE
mcp_client-0.1.0.dist-info/METADATA
mcp_client-0.1.0.dist-info/WHEEL
mcp_client-0.1.0.dist-info/top_level.txt
mcp_client-0.1.0.dist-info/RECORD
