Metadata-Version: 2.2
Name: mcp-client
Version: 0.1.0
Summary: Python client for Unity MCP server
Home-page: https://github.com/lhemerly/mcp-client
Author: Luiz Hemerly
Author-email: Luiz Hemerly <lechemerly@gmail.com>
License: MIT License
Project-URL: Homepage, https://github.com/lhemerly/mcp-client
Project-URL: Repository, https://github.com/lhemerly/mcp-client
Requires-Python: >=3.7
License-File: LICENSE
Requires-Dist: requests
Dynamic: author
Dynamic: home-page
Dynamic: requires-python
